pyproject.toml
setup.cfg
setup.py
Laminos/__init__.py
Laminos/acm.py
Laminos/client.py
Laminos/socket.py
Laminos/sub_client.py
Laminoss.egg-info/PKG-INFO
Laminoss.egg-info/SOURCES.txt
Laminoss.egg-info/dependency_links.txt
Laminoss.egg-info/top_level.txt