Metadata-Version: 2.1
Name: Laminoss
Version: 1.2.17.1
Summary: wth
Home-page: UNKNOWN
Author: ImDefead
Author-email: laminos@inbox.ru
License: UNKNOWN
Platform: UNKNOWN
Classifier: Programming Language :: Python :: 3
Classifier: License :: OSI Approved :: MIT License
Classifier: Operating System :: OS Independent
Requires-Python: >=3.6
